taskyto/__init__.py
taskyto/main.py
taskyto/mutator.py
taskyto/recording.py
taskyto/run_examples.py
taskyto/serve.py
taskyto/spec.py
taskyto/utils.py
taskyto/engine/__init__.py
taskyto/engine/common/__init__.py
taskyto/engine/common/configuration.py
taskyto/engine/common/evaluator.py
taskyto/engine/common/llm.py
taskyto/engine/common/logger.py
taskyto/engine/common/memory.py
taskyto/engine/common/prompts.py
taskyto/engine/common/validator.py
taskyto/engine/custom/__init__.py
taskyto/engine/custom/engine.py
taskyto/engine/custom/events.py
taskyto/engine/custom/generator.py
taskyto/engine/custom/runtime.py
taskyto/engine/custom/statemachine.py
taskyto/engine/custom/tasks.py
taskyto/engine/rag/__init__.py
taskyto/engine/rag/embeddings.py
taskyto/engine/rag/loader.py
taskyto/extensions/__init__.py
taskyto/extensions/extension.py
taskyto/extensions/ollama_extension/__init__.py
taskyto/server/__init__.py
taskyto/testing/__init__.py
taskyto/testing/reader.py
taskyto/testing/test_config_model.py
taskyto/testing/test_engine.py
taskyto/testing/test_model.py
taskyto-0.1.0.dist-info/METADATA
taskyto-0.1.0.dist-info/WHEEL
taskyto-0.1.0.dist-info/entry_points.txt
taskyto-0.1.0.dist-info/top_level.txt
taskyto-0.1.0.dist-info/RECORD
