Metadata-Version: 2.4
Name: taskyto
Version: 0.1.0
Summary: A tool to build chatbots
Author-email: Jesús Sánchez Cuadrado <jesusc@um.es>, Juan de Lara <juan.delara@uam.es>, Esther Guerra <esther.guerra@uam.es>
Keywords: chatbots,AI,tasks
Requires-Python: >=3.8
Requires-Dist: langchain==0.3.10
Requires-Dist: langchain_community==0.3.10
Requires-Dist: langchain-openai==0.2.2
Requires-Dist: langchain_chroma
Requires-Dist: networkx==3.1
Requires-Dist: pydantic==2.9.2
Requires-Dist: pytest==7.4.2
Requires-Dist: PyYAML==6.0.1
Requires-Dist: pydot==1.4.2
Requires-Dist: colorama==0.4.6
Requires-Dist: duckling==1.8.0
Requires-Dist: ctparse==0.3.6
Requires-Dist: alignment==1.0.10
Requires-Dist: python-dateutil~=2.8.2
Requires-Dist: flask
